setup.py
rogoto_core/__init__.py
rogoto_core/rogoto.py
rogoto_core.egg-info/PKG-INFO
rogoto_core.egg-info/SOURCES.txt
rogoto_core.egg-info/dependency_links.txt
rogoto_core.egg-info/not-zip-safe
rogoto_core.egg-info/top_level.txt