Metadata-Version: 1.1
Name: rogoto-core
Version: 0.2.1
Summary: Rogoto Core library that drives the BrickPI
Home-page: https://github.com/AutomatedTester/rogoto-core
Author: David Burns
Author-email: david.burns@theautomatedtester.co.uk
License: Apache
Keywords: brickpi
Platform: UNKNOWN
Classifier: Development Status :: 2 - Pre-Alpha
Classifier: License :: OSI Approved :: Apache Software License
Classifier: Operating System :: POSIX :: Linux
